evadb/__init__.py
evadb/constants.py
evadb/database.py
evadb/evadb_cmd_client.py
evadb/evadb_config.py
evadb/evadb_server.py
evadb/version.py
evadb/binder/__init__.py
evadb/binder/binder_utils.py
evadb/binder/create_index_statement_binder.py
evadb/binder/function_expression_binder.py
evadb/binder/statement_binder.py
evadb/binder/statement_binder_context.py
evadb/binder/tuple_value_expression_binder.py
evadb/catalog/__init__.py
evadb/catalog/catalog_manager.py
evadb/catalog/catalog_type.py
evadb/catalog/catalog_utils.py
evadb/catalog/schema_utils.py
evadb/catalog/sql_config.py
evadb/catalog/models/__init__.py
evadb/catalog/models/association_models.py
evadb/catalog/models/base_model.py
evadb/catalog/models/column_catalog.py
evadb/catalog/models/configuration_catalog.py
evadb/catalog/models/database_catalog.py
evadb/catalog/models/function_cache_catalog.py
evadb/catalog/models/function_catalog.py
evadb/catalog/models/function_cost_catalog.py
evadb/catalog/models/function_io_catalog.py
evadb/catalog/models/function_metadata_catalog.py
evadb/catalog/models/index_catalog.py
evadb/catalog/models/job_catalog.py
evadb/catalog/models/job_history_catalog.py
evadb/catalog/models/table_catalog.py
evadb/catalog/models/utils.py
evadb/catalog/services/__init__.py
evadb/catalog/services/base_service.py
evadb/catalog/services/column_catalog_service.py
evadb/catalog/services/configuration_catalog_service.py
evadb/catalog/services/database_catalog_service.py
evadb/catalog/services/function_cache_catalog_service.py
evadb/catalog/services/function_catalog_service.py
evadb/catalog/services/function_cost_catalog_service.py
evadb/catalog/services/function_io_catalog_service.py
evadb/catalog/services/function_metadata_catalog_service.py
evadb/catalog/services/index_catalog_service.py
evadb/catalog/services/job_catalog_service.py
evadb/catalog/services/job_history_catalog_service.py
evadb/catalog/services/table_catalog_service.py
evadb/configuration/__init__.py
evadb-0.3.9.dist-info/LICENSE.txt
evadb-0.3.9.dist-info/METADATA
evadb-0.3.9.dist-info/WHEEL
evadb-0.3.9.dist-info/entry_points.txt
evadb-0.3.9.dist-info/top_level.txt
evadb-0.3.9.dist-info/RECORD
