Metadata-Version: 2.1
Name: evadb
Version: 0.3.9
Summary: EvaDB AI-Relational Database System
Home-page: https://github.com/georgia-tech-db/eva
Author: Georgia Tech Database Group
Author-email: arulraj@gatech.edu
License: Apache License 2.0
Download-URL: https://github.com/georgia-tech-db/eva
Platform: UNKNOWN
Classifier: Development Status :: 5 - Production/Stable
Classifier: License :: OSI Approved :: Apache Software License
Classifier: Programming Language :: Python :: 3.8
Classifier: Programming Language :: Python :: 3.9
Classifier: Programming Language :: Python :: 3.10
Requires-Python: >=3.8
Provides-Extra: chromadb
Provides-Extra: dev
Provides-Extra: document
Provides-Extra: forecasting
Provides-Extra: function
Provides-Extra: ludwig
Provides-Extra: milvus
Provides-Extra: notebook
Provides-Extra: pinecone
Provides-Extra: postgres
Provides-Extra: qdrant
Provides-Extra: ray
Provides-Extra: sklearn
Provides-Extra: vision
Provides-Extra: xgboost
License-File: LICENSE.txt
